{
	"configurations" : 
	[
		{
			"directories" : 
			[
				{
					"build" : ".",
					"childIndexes" : 
					[
						1
					],
					"hasInstallRule" : true,
					"jsonFile" : "directory-.-Debug-cbe6f86fdf904fe23a4b.json",
					"minimumCMakeVersion" : 
					{
						"string" : "3.0.2"
					},
					"projectIndex" : 0,
					"source" : ".",
					"targetIndexes" : 
					[
						0,
						1,
						2,
						3,
						4,
						5,
						6,
						7,
						8,
						13,
						14,
						15,
						16,
						17,
						18,
						19,
						20,
						21,
						22,
						23,
						24,
						25,
						26,
						27,
						28,
						29,
						30,
						31,
						32,
						33,
						34,
						35,
						36,
						37,
						38,
						39
					]
				},
				{
					"build" : "gtest",
					"childIndexes" : 
					[
						2
					],
					"jsonFile" : "directory-gtest-Debug-40f9edd0af6c04d6f946.json",
					"minimumCMakeVersion" : 
					{
						"string" : "2.8.8"
					},
					"parentIndex" : 0,
					"projectIndex" : 1,
					"source" : "/usr/src/googletest"
				},
				{
					"build" : "gtest/googlemock",
					"childIndexes" : 
					[
						3
					],
					"jsonFile" : "directory-gtest.googlemock-Debug-8fd0af86403c015b5fbc.json",
					"minimumCMakeVersion" : 
					{
						"string" : "2.6.4"
					},
					"parentIndex" : 1,
					"projectIndex" : 2,
					"source" : "/usr/src/googletest/googlemock",
					"targetIndexes" : 
					[
						9,
						10
					]
				},
				{
					"build" : "gtest/googletest",
					"jsonFile" : "directory-gtest.googletest-Debug-5804ba12edef54b53d36.json",
					"minimumCMakeVersion" : 
					{
						"string" : "2.6.4"
					},
					"parentIndex" : 2,
					"projectIndex" : 3,
					"source" : "/usr/src/googletest/googletest",
					"targetIndexes" : 
					[
						11,
						12
					]
				}
			],
			"name" : "Debug",
			"projects" : 
			[
				{
					"childIndexes" : 
					[
						1
					],
					"directoryIndexes" : 
					[
						0
					],
					"name" : "evs",
					"targetIndexes" : 
					[
						0,
						1,
						2,
						3,
						4,
						5,
						6,
						7,
						8,
						13,
						14,
						15,
						16,
						17,
						18,
						19,
						20,
						21,
						22,
						23,
						24,
						25,
						26,
						27,
						28,
						29,
						30,
						31,
						32,
						33,
						34,
						35,
						36,
						37,
						38,
						39
					]
				},
				{
					"childIndexes" : 
					[
						2
					],
					"directoryIndexes" : 
					[
						1
					],
					"name" : "googletest-distribution",
					"parentIndex" : 0
				},
				{
					"childIndexes" : 
					[
						3
					],
					"directoryIndexes" : 
					[
						2
					],
					"name" : "gmock",
					"parentIndex" : 1,
					"targetIndexes" : 
					[
						9,
						10
					]
				},
				{
					"directoryIndexes" : 
					[
						3
					],
					"name" : "gtest",
					"parentIndex" : 2,
					"targetIndexes" : 
					[
						11,
						12
					]
				}
			],
			"targets" : 
			[
				{
					"directoryIndex" : 0,
					"id" : "clean_test_results::@6890427a1f51a3e7e1df",
					"jsonFile" : "target-clean_test_results-Debug-9082e674e1348ccc8007.json",
					"name" : "clean_test_results",
					"projectIndex" : 0
				},
				{
					"directoryIndex" : 0,
					"id" : "download_extra_data::@6890427a1f51a3e7e1df",
					"jsonFile" : "target-download_extra_data-Debug-9c004c066442ffd3f9a6.json",
					"name" : "download_extra_data",
					"projectIndex" : 0
				},
				{
					"directoryIndex" : 0,
					"id" : "doxygen::@6890427a1f51a3e7e1df",
					"jsonFile" : "target-doxygen-Debug-8afb2dd64d0cd4a59f1c.json",
					"name" : "doxygen",
					"projectIndex" : 0
				},
				{
					"directoryIndex" : 0,
					"id" : "evs_reference_trajectory::@6890427a1f51a3e7e1df",
					"jsonFile" : "target-evs_reference_trajectory-Debug-e878275c9a2f4fdb7628.json",
					"name" : "evs_reference_trajectory",
					"projectIndex" : 0
				},
				{
					"directoryIndex" : 0,
					"id" : "geometry_msgs_generate_messages_cpp::@6890427a1f51a3e7e1df",
					"jsonFile" : "target-geometry_msgs_generate_messages_cpp-Debug-7bdb1b9ccc80eec1ab0b.json",
					"name" : "geometry_msgs_generate_messages_cpp",
					"projectIndex" : 0
				},
				{
					"directoryIndex" : 0,
					"id" : "geometry_msgs_generate_messages_eus::@6890427a1f51a3e7e1df",
					"jsonFile" : "target-geometry_msgs_generate_messages_eus-Debug-ff7a43d7b40f08fff80e.json",
					"name" : "geometry_msgs_generate_messages_eus",
					"projectIndex" : 0
				},
				{
					"directoryIndex" : 0,
					"id" : "geometry_msgs_generate_messages_lisp::@6890427a1f51a3e7e1df",
					"jsonFile" : "target-geometry_msgs_generate_messages_lisp-Debug-2406285756f3c5ec626b.json",
					"name" : "geometry_msgs_generate_messages_lisp",
					"projectIndex" : 0
				},
				{
					"directoryIndex" : 0,
					"id" : "geometry_msgs_generate_messages_nodejs::@6890427a1f51a3e7e1df",
					"jsonFile" : "target-geometry_msgs_generate_messages_nodejs-Debug-66cc885d0bc42c1aa354.json",
					"name" : "geometry_msgs_generate_messages_nodejs",
					"projectIndex" : 0
				},
				{
					"directoryIndex" : 0,
					"id" : "geometry_msgs_generate_messages_py::@6890427a1f51a3e7e1df",
					"jsonFile" : "target-geometry_msgs_generate_messages_py-Debug-529c975dc55e9b032504.json",
					"name" : "geometry_msgs_generate_messages_py",
					"projectIndex" : 0
				},
				{
					"directoryIndex" : 2,
					"id" : "gmock::@e3f94eedc5dc07131386",
					"jsonFile" : "target-gmock-Debug-31741966239e1ec3e530.json",
					"name" : "gmock",
					"projectIndex" : 2
				},
				{
					"directoryIndex" : 2,
					"id" : "gmock_main::@e3f94eedc5dc07131386",
					"jsonFile" : "target-gmock_main-Debug-5f81ccc70b506ab3d647.json",
					"name" : "gmock_main",
					"projectIndex" : 2
				},
				{
					"directoryIndex" : 3,
					"id" : "gtest::@b738d542747fbb7ea6e3",
					"jsonFile" : "target-gtest-Debug-1ef4e3367fb36ac3d0e2.json",
					"name" : "gtest",
					"projectIndex" : 3
				},
				{
					"directoryIndex" : 3,
					"id" : "gtest_main::@b738d542747fbb7ea6e3",
					"jsonFile" : "target-gtest_main-Debug-e647b0ad2c32090c3ea4.json",
					"name" : "gtest_main",
					"projectIndex" : 3
				},
				{
					"directoryIndex" : 0,
					"id" : "roscpp_generate_messages_cpp::@6890427a1f51a3e7e1df",
					"jsonFile" : "target-roscpp_generate_messages_cpp-Debug-4dbec73cae7b1649fd44.json",
					"name" : "roscpp_generate_messages_cpp",
					"projectIndex" : 0
				},
				{
					"directoryIndex" : 0,
					"id" : "roscpp_generate_messages_eus::@6890427a1f51a3e7e1df",
					"jsonFile" : "target-roscpp_generate_messages_eus-Debug-688e05b743981ad249a2.json",
					"name" : "roscpp_generate_messages_eus",
					"projectIndex" : 0
				},
				{
					"directoryIndex" : 0,
					"id" : "roscpp_generate_messages_lisp::@6890427a1f51a3e7e1df",
					"jsonFile" : "target-roscpp_generate_messages_lisp-Debug-dde9083c26be7941f73b.json",
					"name" : "roscpp_generate_messages_lisp",
					"projectIndex" : 0
				},
				{
					"directoryIndex" : 0,
					"id" : "roscpp_generate_messages_nodejs::@6890427a1f51a3e7e1df",
					"jsonFile" : "target-roscpp_generate_messages_nodejs-Debug-ccde6ed1949ff25c18c0.json",
					"name" : "roscpp_generate_messages_nodejs",
					"projectIndex" : 0
				},
				{
					"directoryIndex" : 0,
					"id" : "roscpp_generate_messages_py::@6890427a1f51a3e7e1df",
					"jsonFile" : "target-roscpp_generate_messages_py-Debug-cdd571527eed5253d42e.json",
					"name" : "roscpp_generate_messages_py",
					"projectIndex" : 0
				},
				{
					"directoryIndex" : 0,
					"id" : "rosgraph_msgs_generate_messages_cpp::@6890427a1f51a3e7e1df",
					"jsonFile" : "target-rosgraph_msgs_generate_messages_cpp-Debug-78148a1ee7486f23c27d.json",
					"name" : "rosgraph_msgs_generate_messages_cpp",
					"projectIndex" : 0
				},
				{
					"directoryIndex" : 0,
					"id" : "rosgraph_msgs_generate_messages_eus::@6890427a1f51a3e7e1df",
					"jsonFile" : "target-rosgraph_msgs_generate_messages_eus-Debug-605f464b9bb6c318a2e7.json",
					"name" : "rosgraph_msgs_generate_messages_eus",
					"projectIndex" : 0
				},
				{
					"directoryIndex" : 0,
					"id" : "rosgraph_msgs_generate_messages_lisp::@6890427a1f51a3e7e1df",
					"jsonFile" : "target-rosgraph_msgs_generate_messages_lisp-Debug-f63ea23608a1830f02b8.json",
					"name" : "rosgraph_msgs_generate_messages_lisp",
					"projectIndex" : 0
				},
				{
					"directoryIndex" : 0,
					"id" : "rosgraph_msgs_generate_messages_nodejs::@6890427a1f51a3e7e1df",
					"jsonFile" : "target-rosgraph_msgs_generate_messages_nodejs-Debug-210d53f32eed9bf1fb60.json",
					"name" : "rosgraph_msgs_generate_messages_nodejs",
					"projectIndex" : 0
				},
				{
					"directoryIndex" : 0,
					"id" : "rosgraph_msgs_generate_messages_py::@6890427a1f51a3e7e1df",
					"jsonFile" : "target-rosgraph_msgs_generate_messages_py-Debug-3d3fbecced88e2a32139.json",
					"name" : "rosgraph_msgs_generate_messages_py",
					"projectIndex" : 0
				},
				{
					"directoryIndex" : 0,
					"id" : "run_tests::@6890427a1f51a3e7e1df",
					"jsonFile" : "target-run_tests-Debug-11e8c302418947de974d.json",
					"name" : "run_tests",
					"projectIndex" : 0
				},
				{
					"directoryIndex" : 0,
					"id" : "std_msgs_generate_messages_cpp::@6890427a1f51a3e7e1df",
					"jsonFile" : "target-std_msgs_generate_messages_cpp-Debug-e78f3c3e2eb921e4a154.json",
					"name" : "std_msgs_generate_messages_cpp",
					"projectIndex" : 0
				},
				{
					"directoryIndex" : 0,
					"id" : "std_msgs_generate_messages_eus::@6890427a1f51a3e7e1df",
					"jsonFile" : "target-std_msgs_generate_messages_eus-Debug-47377ba79d4fbe82ee91.json",
					"name" : "std_msgs_generate_messages_eus",
					"projectIndex" : 0
				},
				{
					"directoryIndex" : 0,
					"id" : "std_msgs_generate_messages_lisp::@6890427a1f51a3e7e1df",
					"jsonFile" : "target-std_msgs_generate_messages_lisp-Debug-36c53bc7674e803a34dc.json",
					"name" : "std_msgs_generate_messages_lisp",
					"projectIndex" : 0
				},
				{
					"directoryIndex" : 0,
					"id" : "std_msgs_generate_messages_nodejs::@6890427a1f51a3e7e1df",
					"jsonFile" : "target-std_msgs_generate_messages_nodejs-Debug-e48744437592dbf81881.json",
					"name" : "std_msgs_generate_messages_nodejs",
					"projectIndex" : 0
				},
				{
					"directoryIndex" : 0,
					"id" : "std_msgs_generate_messages_py::@6890427a1f51a3e7e1df",
					"jsonFile" : "target-std_msgs_generate_messages_py-Debug-72a7bb947aa1e1c5ab1e.json",
					"name" : "std_msgs_generate_messages_py",
					"projectIndex" : 0
				},
				{
					"directoryIndex" : 0,
					"id" : "std_srvs_generate_messages_cpp::@6890427a1f51a3e7e1df",
					"jsonFile" : "target-std_srvs_generate_messages_cpp-Debug-e4c1f5957def9f217cba.json",
					"name" : "std_srvs_generate_messages_cpp",
					"projectIndex" : 0
				},
				{
					"directoryIndex" : 0,
					"id" : "std_srvs_generate_messages_eus::@6890427a1f51a3e7e1df",
					"jsonFile" : "target-std_srvs_generate_messages_eus-Debug-d0961cdd67ba29d3fc10.json",
					"name" : "std_srvs_generate_messages_eus",
					"projectIndex" : 0
				},
				{
					"directoryIndex" : 0,
					"id" : "std_srvs_generate_messages_lisp::@6890427a1f51a3e7e1df",
					"jsonFile" : "target-std_srvs_generate_messages_lisp-Debug-c2913292d7bf988854e3.json",
					"name" : "std_srvs_generate_messages_lisp",
					"projectIndex" : 0
				},
				{
					"directoryIndex" : 0,
					"id" : "std_srvs_generate_messages_nodejs::@6890427a1f51a3e7e1df",
					"jsonFile" : "target-std_srvs_generate_messages_nodejs-Debug-55bef9c414ff26ce3c5f.json",
					"name" : "std_srvs_generate_messages_nodejs",
					"projectIndex" : 0
				},
				{
					"directoryIndex" : 0,
					"id" : "std_srvs_generate_messages_py::@6890427a1f51a3e7e1df",
					"jsonFile" : "target-std_srvs_generate_messages_py-Debug-c68df9e19b5445011801.json",
					"name" : "std_srvs_generate_messages_py",
					"projectIndex" : 0
				},
				{
					"directoryIndex" : 0,
					"id" : "tests::@6890427a1f51a3e7e1df",
					"jsonFile" : "target-tests-Debug-f11c9d6fe22c5df83853.json",
					"name" : "tests",
					"projectIndex" : 0
				},
				{
					"directoryIndex" : 0,
					"id" : "topic_tools_generate_messages_cpp::@6890427a1f51a3e7e1df",
					"jsonFile" : "target-topic_tools_generate_messages_cpp-Debug-3bf3a146e5ea7673f5e2.json",
					"name" : "topic_tools_generate_messages_cpp",
					"projectIndex" : 0
				},
				{
					"directoryIndex" : 0,
					"id" : "topic_tools_generate_messages_eus::@6890427a1f51a3e7e1df",
					"jsonFile" : "target-topic_tools_generate_messages_eus-Debug-26ab211ba1da9d18f382.json",
					"name" : "topic_tools_generate_messages_eus",
					"projectIndex" : 0
				},
				{
					"directoryIndex" : 0,
					"id" : "topic_tools_generate_messages_lisp::@6890427a1f51a3e7e1df",
					"jsonFile" : "target-topic_tools_generate_messages_lisp-Debug-aca72b26227e94a45b0c.json",
					"name" : "topic_tools_generate_messages_lisp",
					"projectIndex" : 0
				},
				{
					"directoryIndex" : 0,
					"id" : "topic_tools_generate_messages_nodejs::@6890427a1f51a3e7e1df",
					"jsonFile" : "target-topic_tools_generate_messages_nodejs-Debug-7cbce8a9ac78ae7d5342.json",
					"name" : "topic_tools_generate_messages_nodejs",
					"projectIndex" : 0
				},
				{
					"directoryIndex" : 0,
					"id" : "topic_tools_generate_messages_py::@6890427a1f51a3e7e1df",
					"jsonFile" : "target-topic_tools_generate_messages_py-Debug-654ec9e3f1ba6e540842.json",
					"name" : "topic_tools_generate_messages_py",
					"projectIndex" : 0
				}
			]
		}
	],
	"kind" : "codemodel",
	"paths" : 
	{
		"build" : "/home/nathan/ROS/Noetic/catkin_ws/src/evs/cmake-build-debug",
		"source" : "/home/nathan/ROS/Noetic/catkin_ws/src/evs"
	},
	"version" : 
	{
		"major" : 2,
		"minor" : 6
	}
}
